galry/__init__.py
galry/bindingmanager.py
galry/colors.py
galry/cursors.py
galry/datanormalizer.py
galry/debugtools.py
galry/galrywidget.py
galry/glrenderer.py
galry/icons.py
galry/interactionmanager.py
galry/manager.py
galry/paintmanager.py
galry/pyplot.py
galry/scene.py
galry/tools.py
galry/useractions.py
galry/cursors/glass.png
galry/cursors/glassmask.png
galry/icons/exit.png
galry/icons/fullscreen.png
galry/icons/grid.png
galry/icons/hand.png
galry/icons/help.png
galry/icons/home.png
galry/icons/move.png
galry/icons/save.png
galry/icons/search.png
galry/icons/selection.png
galry/icons/toolbar.png
galry/managers/__init__.py
galry/managers/default_manager.py
galry/managers/mesh_manager.py
galry/managers/plot_manager.py
galry/processors/__init__.py
galry/processors/default_processor.py
galry/processors/grid_processor.py
galry/processors/mesh_processor.py
galry/processors/navigation_processor.py
galry/processors/processor.py
galry/test/__init__.py
galry/test/empty_test.py
galry/test/plot_colormap_test.py
galry/test/plot_default_test.py
galry/test/plot_double_test.py
galry/test/plot_indexed_test.py
galry/test/plot_lines_test.py
galry/test/plot_multi_slice_test.py
galry/test/plot_multi_test.py
galry/test/plot_points_test.py
galry/test/plot_ref_test.py
galry/test/plot_ref_update_test.py
galry/test/plot_reinit_test.py
galry/test/plot_slice_test.py
galry/test/plot_update_indexed_test.py
galry/test/rectangles_default_test.py
galry/test/sprite_default_test.py
galry/test/test.py
galry/test/text_default_test.py
galry/test/text_multi_test.py
galry/test/texture1D_test.py
galry/test/texture_default_test.py
galry/test/texture_reinit_test.py
galry/test/threedimensions_default_test.py
galry/test/update_default_test.py
galry/test/update_text_test.py
galry/test/update_texture_rectangle_test.py
galry/test/update_texture_test.py
galry/test/autosave/EmptyTest.REF.png
galry/test/autosave/TextDefaultTest.REF.png
galry-0.3.1.dist-info/DESCRIPTION.rst
galry-0.3.1.dist-info/METADATA
galry-0.3.1.dist-info/RECORD
galry-0.3.1.dist-info/WHEEL
galry-0.3.1.dist-info/metadata.json
galry-0.3.1.dist-info/top_level.txt
