Metadata-Version: 2.0
Name: galry
Version: 0.3.1
Summary: High-performance interactive visualization in Python.
Home-page: https://github.com/rossant/galry
Author: Cyrille Rossant
Author-email: rossant@github
License: LICENSE.md
Platform: UNKNOWN
